setup.py
pwserver/__init__.py
pwserver/config.py
pwserver/main.py
pwserverd.egg-info/PKG-INFO
pwserverd.egg-info/SOURCES.txt
pwserverd.egg-info/dependency_links.txt
pwserverd.egg-info/entry_points.txt
pwserverd.egg-info/requires.txt
pwserverd.egg-info/top_level.txt