Metadata-Version: 1.0
Name: pwserverd
Version: 0.1
Summary: Password generation and security checking server
Home-page: http://alastairs-place.net/pwserverd
Author: Alastair Houghton
Author-email: alastair@alastairs-place.net
License: MIT License
Platform: UNKNOWN
Classifier: Development Status :: 4 - Beta
Classifier: Intended Audience :: Developers
Classifier: License :: OSI Approved :: MIT License
Classifier: Topic :: System
